OPQL/SQLITEResolver.py
OPQL/__init__.py
OPQL/contextoperations.py
OPQL/ocelimport.py
OPQL/ocellog.py
OPQL/query.py
OPQL/query_expression.py
OPQL/query_pattern.py
OPQL/querycontext.py
OPQL/querysolver.py
OPQL/util.py
OPQL/visitor.py
OPQL/grammar/OPQLLexer.py
OPQL/grammar/OPQLParser.py
OPQL/grammar/OPQLVisitor.py
OPQL-0.1.1.dist-info/LICENSE
OPQL-0.1.1.dist-info/METADATA
OPQL-0.1.1.dist-info/WHEEL
OPQL-0.1.1.dist-info/top_level.txt
OPQL-0.1.1.dist-info/RECORD
