Metadata-Version: 2.1
Name: OPQL
Version: 0.1.1
Summary: An Object-Centric Process Query Language
Author-email: Patric Mai <patric.mai@gmx.de>
License: GNU AFFERO GENERAL PUBLIC LICENSE
Project-URL: Homepage, https://gitlab.com/p.mai/opql
Project-URL: Issues, https://gitlab.com/p.mai/opql/issues
Classifier: Programming Language :: Python :: 3
Classifier: License :: OSI Approved :: GNU Affero General Public License v3 or later (AGPLv3+)
Classifier: Operating System :: OS Independent
Requires-Python: >=3.11
License-File: LICENSE
Requires-Dist: pandas
Requires-Dist: antlr4-python3-runtime
